setup.py
samsungctl/__init__.py
samsungctl/__main__.py
samsungctl/interactive.py
samsungctl/remote.py
samsungctl.egg-info/PKG-INFO
samsungctl.egg-info/SOURCES.txt
samsungctl.egg-info/dependency_links.txt
samsungctl.egg-info/entry_points.txt
samsungctl.egg-info/top_level.txt