Metadata-Version: 1.1
Name: samsungctl
Version: 0.4.0
Summary: Remote control Samsung televisions via TCP/IP connection
Home-page: https://github.com/Ape/samsungctl
Author: Lauri Niskanen
Author-email: ape@ape3000.com
License: MIT
Platform: UNKNOWN
Classifier: Development Status :: 4 - Beta
Classifier: Environment :: Console
Classifier: License :: OSI Approved :: MIT License
Classifier: Programming Language :: Python :: 3
Classifier: Topic :: Home Automation
